mcap/__init__.py
mcap/_chunk_builder.py
mcap/_message_queue.py
mcap/data_stream.py
mcap/decoder.py
mcap/exceptions.py
mcap/opcode.py
mcap/py.typed
mcap/reader.py
mcap/records.py
mcap/serialization.py
mcap/stream_reader.py
mcap/summary.py
mcap/well_known.py
mcap/writer.py
mcap-1.3.1.dist-info/METADATA
mcap-1.3.1.dist-info/WHEEL
mcap-1.3.1.dist-info/top_level.txt
mcap-1.3.1.dist-info/RECORD
