Metadata-Version: 2.1
Name: mcap
Version: 1.3.1
Summary: MCAP libraries for Python
Home-page: https://github.com/foxglove/mcap
Classifier: Programming Language :: Python :: 3
Classifier: License :: OSI Approved :: MIT License
Classifier: Operating System :: OS Independent
Requires-Python: >=3.7
Requires-Dist: lz4
Requires-Dist: zstandard
